calmjs.webpack-1.2.0-py3.6-nspkg.pth
calmjs/webpack/README.rst
calmjs/webpack/__init__.py
calmjs/webpack/artifact.py
calmjs/webpack/base.py
calmjs/webpack/cli.py
calmjs/webpack/configuration.py
calmjs/webpack/dev.py
calmjs/webpack/dist.py
calmjs/webpack/env.py
calmjs/webpack/exc.py
calmjs/webpack/interrogation.py
calmjs/webpack/loaderplugin.py
calmjs/webpack/manipulation.py
calmjs/webpack/runtime.py
calmjs/webpack/toolchain.py
calmjs/webpack/walkers.py
calmjs/webpack/testing/__init__.py
calmjs/webpack/testing/utils.py
calmjs/webpack/testing/examples/README.rst
calmjs/webpack/testing/examples/empty_package.js
calmjs/webpack/testing/examples/example_package.mangled.js
calmjs/webpack/testing/examples/typical_names.js
calmjs/webpack/testing/examples/unusual_names.js
calmjs/webpack/testing/examples/2.7/example_package.extras.js
calmjs/webpack/testing/examples/2.7/example_package.extras.min.js
calmjs/webpack/testing/examples/2.7/example_package.js
calmjs/webpack/testing/examples/2.7/example_package.min.js
calmjs/webpack/testing/examples/3.12/example_package.extras.js
calmjs/webpack/testing/examples/3.12/example_package.extras.min.js
calmjs/webpack/testing/examples/3.12/example_package.js
calmjs/webpack/testing/examples/3.12/example_package.min.js
calmjs/webpack/testing/examples/4.0/example_package.extras.js
calmjs/webpack/testing/examples/4.0/example_package.extras.min.js
calmjs/webpack/testing/examples/4.0/example_package.js
calmjs/webpack/testing/examples/4.0/example_package.min.js
calmjs/webpack/testing/examples/4.16/example_package.extras.js
calmjs/webpack/testing/examples/4.16/example_package.extras.min.js
calmjs/webpack/testing/examples/4.16/example_package.js
calmjs/webpack/testing/examples/4.16/example_package.min.js
calmjs/webpack/tests/__init__.py
calmjs/webpack/tests/test_cli.py
calmjs/webpack/tests/test_configuration.py
calmjs/webpack/tests/test_dev.py
calmjs/webpack/tests/test_dist.py
calmjs.webpack-1.2.0.dist-info/METADATA
calmjs.webpack-1.2.0.dist-info/RECORD
calmjs.webpack-1.2.0.dist-info/WHEEL
calmjs.webpack-1.2.0.dist-info/calmjs_module_registry.txt
calmjs.webpack-1.2.0.dist-info/entry_points.txt
calmjs.webpack-1.2.0.dist-info/namespace_packages.txt
calmjs.webpack-1.2.0.dist-info/package.json
calmjs.webpack-1.2.0.dist-info/top_level.txt
