Metadata-Version: 2.1
Name: calmjs.webpack
Version: 1.2.0
Summary: Package for extending the Calmjs framework to support the usage of webpack for the generation of deployable artifacts from JavaScript source code provided by Python packages in conjunction with standard JavaScript or Node.js packages sourced from npm or other similar package repositories.
Home-page: https://github.com/calmjs/calmjs.webpack
Author: Tommy Yu
Author-email: tommy.yu@auckland.ac.nz
License: gpl
Platform: UNKNOWN
Classifier: Development Status :: 5 - Production/Stable
Classifier: Environment :: Console
Classifier: Environment :: Plugins
Classifier: Framework :: Setuptools Plugin
Classifier: Intended Audience :: Developers
Classifier: License :: OSI Approved :: GNU General Public License v2 or later (GPLv2+)
Classifier: Operating System :: MacOS :: MacOS X
Classifier: Operating System :: Microsoft :: Windows
Classifier: Operating System :: POSIX
Classifier: Operating System :: POSIX :: BSD
Classifier: Operating System :: POSIX :: Linux
Classifier: Operating System :: OS Independent
Classifier: Programming Language :: JavaScript
Classifier: Programming Language :: Python
Classifier: Programming Language :: Python :: 2
Classifier: Programming Language :: Python :: 2.7
Classifier: Programming Language :: Python :: 3
Classifier: Programming Language :: Python :: 3.4
Classifier: Programming Language :: Python :: 3.5
Classifier: Programming Language :: Python :: 3.6
Classifier: Programming Language :: Python :: 3.7
Classifier: Programming Language :: Python :: Implementation :: CPython
Classifier: Programming Language :: Python :: Implementation :: PyPy
Classifier: Topic :: Software Development :: Build Tools
Classifier: Topic :: System :: Software Distribution
Classifier: Topic :: Utilities
Provides-Extra: dev
Requires-Dist: calmjs (>=3.3.1)
Provides-Extra: dev
Requires-Dist: calmjs.dev (<3,>=2.2.2); extra == 'dev'
